astrix/__init__.py
astrix/cli.py
astrix/features/callgraph.py
astrix/features/class_heirarchy.py
astrix/features/code_quality.py
astrix/features/conflict_management.py
astrix/features/dependency.py
astrix/features/dependency_analysis.py
astrix-0.1.7.dist-info/entry_points.txt
astrix-0.1.7.dist-info/METADATA
astrix-0.1.7.dist-info/WHEEL
astrix-0.1.7.dist-info/RECORD
