Metadata-Version: 2.1
Name: astrix
Version: 0.1.7
Summary: Your All-in-One Python Project Analyzer
Author: Ashwin
Author-email: ashwinrb74@gmail.com
Requires-Python: >=3.10,<4.0
Classifier: Programming Language :: Python :: 3
Classifier: Programming Language :: Python :: 3.10
Classifier: Programming Language :: Python :: 3.11
Classifier: Programming Language :: Python :: 3.12
Requires-Dist: click (>=8.1.7,<9.0.0)
Requires-Dist: matplotlib (>=3.9.2,<4.0.0)
Requires-Dist: networkx (>=3.3,<4.0)
Requires-Dist: pytest (>=8.3.3,<9.0.0)
Requires-Dist: radon (>=6.0.1,<7.0.0)
Requires-Dist: requests (>=2.32.3,<3.0.0)
Requires-Dist: stdlib-list (>=0.10.0,<0.11.0)
Requires-Dist: tabulate (>=0.9.0,<0.10.0)
Requires-Dist: toml (>=0.10.2,<0.11.0)
